pynessie/__init__.py
pynessie/cli.py
pynessie/cli_common_context.py
pynessie/decorators.py
pynessie/error.py
pynessie/model.py
pynessie/types.py
pynessie/auth/__init__.py
pynessie/auth/aws.py
pynessie/auth/bearer.py
pynessie/auth/config.py
pynessie/client/__init__.py
pynessie/client/_endpoints.py
pynessie/client/nessie_client.py
pynessie/commands/__init__.py
pynessie/commands/_branch_tag_handlers.py
pynessie/commands/branch.py
pynessie/commands/cherry_pick.py
pynessie/commands/config.py
pynessie/commands/diff.py
pynessie/commands/log.py
pynessie/commands/merge.py
pynessie/commands/remote.py
pynessie/commands/tag.py
pynessie/commands/content/__init__.py
pynessie/commands/content/commit.py
pynessie/commands/content/list_.py
pynessie/commands/content/view.py
pynessie/conf/__init__.py
pynessie/conf/config_command.py
pynessie/conf/config_default.yaml
pynessie/conf/config_parser.py
pynessie/conf/io.py
pynessie/utils/__init__.py
pynessie/utils/expression_util.py
pynessie-0.67.0.dist-info/AUTHORS.rst
pynessie-0.67.0.dist-info/LICENSE
pynessie-0.67.0.dist-info/METADATA
pynessie-0.67.0.dist-info/NOTICE
pynessie-0.67.0.dist-info/WHEEL
pynessie-0.67.0.dist-info/entry_points.txt
pynessie-0.67.0.dist-info/top_level.txt
pynessie-0.67.0.dist-info/RECORD
