Metadata-Version: 2.1
Name: pynessie
Version: 0.67.0
Summary: Project Nessie: Transactional Catalog for Data Lakes with Git-like semantics
Home-page: https://github.com/projectnessie/nessie
Author: Ryan Murray
Author-email: nessie-release-builder@dremio.com
License: Apache Software License 2.0
Keywords: pynessie
Platform: UNKNOWN
Classifier: Development Status :: 2 - Pre-Alpha
Classifier: Intended Audience :: Developers
Classifier: License :: OSI Approved :: Apache Software License
Classifier: Natural Language :: English
Classifier: Programming Language :: Python :: 3
Classifier: Programming Language :: Python :: 3.8
Classifier: Programming Language :: Python :: 3.9
Classifier: Programming Language :: Python :: 3.10
Classifier: Programming Language :: Python :: 3.11
Classifier: Programming Language :: Python :: 3.12
Requires-Python: >=3.8
Requires-Dist: attrs
Requires-Dist: botocore
Requires-Dist: Click <9.0.0,>6.0.0
Requires-Dist: confuse ==2.0.1
Requires-Dist: desert
Requires-Dist: marshmallow
Requires-Dist: marshmallow-oneofschema
Requires-Dist: python-dateutil
Requires-Dist: requests
Requires-Dist: requests-aws4auth
Requires-Dist: simplejson
